mzt_kong/KongClient.py
mzt_kong/__init__.py
mzt_kong-1.1.dist-info/LICENSE
mzt_kong-1.1.dist-info/METADATA
mzt_kong-1.1.dist-info/WHEEL
mzt_kong-1.1.dist-info/top_level.txt
mzt_kong-1.1.dist-info/RECORD
