Metadata-Version: 2.1
Name: mzt-kong
Version: 1.1
Summary: UNKNOWN
Home-page: UNKNOWN
Author: UNKNOWN
Author-email: UNKNOWN
License: UNKNOWN
Platform: UNKNOWN
Requires-Dist: mzt-http-utils
